concurrent_log_handler/__init__.py
concurrent_log_handler/__version__.py
concurrent_log_handler/py.typed
concurrent_log_handler/queue.py
concurrent_log_handler-0.9.27.dist-info/METADATA
concurrent_log_handler-0.9.27.dist-info/WHEEL
concurrent_log_handler-0.9.27.dist-info/licenses/LICENSE
concurrent_log_handler-0.9.27.dist-info/RECORD
