Metadata-Version: 2.4
Name: concurrent-log-handler
Version: 0.9.27
Summary: RotatingFileHandler replacement with concurrency, gzip and Windows support. Size and time based rotation.
Project-URL: Homepage, https://github.com/Preston-Landers/concurrent-log-handler
Author-email: Preston Landers <planders@utexas.edu>
License-Expression: Apache-2.0
License-File: LICENSE
Keywords: QueueHandler,QueueListener,linux,logging,portalocker,rotate,unix,windows
Classifier: Development Status :: 4 - Beta
Classifier: License :: OSI Approved :: Apache Software License
Classifier: Operating System :: Microsoft :: Windows
Classifier: Operating System :: POSIX
Classifier: Programming Language :: Python
Classifier: Programming Language :: Python :: 3
Classifier: Programming Language :: Python :: 3.6
Classifier: Programming Language :: Python :: 3.7
Classifier: Programming Language :: Python :: 3.8
Classifier: Programming Language :: Python :: 3.9
Classifier: Programming Language :: Python :: 3.10
Classifier: Programming Language :: Python :: 3.11
Classifier: Programming Language :: Python :: 3.12
Classifier: Programming Language :: Python :: 3.13
Classifier: Topic :: Software Development :: Libraries :: Python Modules
Classifier: Topic :: System :: Logging
Requires-Python: >=3.6
Requires-Dist: portalocker>=1.6.0
Provides-Extra: dev
Requires-Dist: black; extra == 'dev'
Requires-Dist: coverage; extra == 'dev'
Requires-Dist: hatch; extra == 'dev'
Requires-Dist: pytest; extra == 'dev'
Requires-Dist: pytest-cov; extra == 'dev'
Requires-Dist: pytest-mock; extra == 'dev'
Requires-Dist: pytest-sugar; extra == 'dev'
Requires-Dist: ruff; extra == 'dev'
